odoo/addons/partner_disable_vat_verification/README.rst
odoo/addons/partner_disable_vat_verification/__init__.py
odoo/addons/partner_disable_vat_verification/__manifest__.py
odoo/addons/partner_disable_vat_verification/models/__init__.py
odoo/addons/partner_disable_vat_verification/models/res_partner.py
odoo/addons/partner_disable_vat_verification/readme/CONFIGURE.md
odoo/addons/partner_disable_vat_verification/readme/CONTRIBUTORS.md
odoo/addons/partner_disable_vat_verification/readme/DESCRIPTION.md
odoo/addons/partner_disable_vat_verification/readme/USAGE.md
odoo/addons/partner_disable_vat_verification/static/description/icon.png
odoo/addons/partner_disable_vat_verification/static/description/index.html
odoo/addons/partner_disable_vat_verification/tests/__init__.py
odoo/addons/partner_disable_vat_verification/tests/test_partner_disable_vat_verification.py
odoo_addon_partner_disable_vat_verification-17.0.1.0.0.1.dist-info/METADATA
odoo_addon_partner_disable_vat_verification-17.0.1.0.0.1.dist-info/WHEEL
odoo_addon_partner_disable_vat_verification-17.0.1.0.0.1.dist-info/top_level.txt
odoo_addon_partner_disable_vat_verification-17.0.1.0.0.1.dist-info/RECORD
